dan/__init__.py
dan/__main__.py
dan/jinja.py
dan/logging.py
dan/make.py
dan/testing.py
dan/autoconf/__init__.py
dan/autoconf/project.py
dan/cli/__init__.py
dan/cli/click.py
dan/cli/io.py
dan/cli/main.py
dan/cli/user.py
dan/cli/vscode.py
dan/cmake/__init__.py
dan/cmake/configure_file.py
dan/cmake/project.py
dan/conan/__init__.py
dan/conan/requirements.py
dan/core/__init__.py
dan/core/aiofiles.py
dan/core/asyncio.py
dan/core/cache.py
dan/core/detect.py
dan/core/diagnostics.py
dan/core/errors.py
dan/core/find.py
dan/core/functools.py
dan/core/generator.py
dan/core/include.py
dan/core/makefile.py
dan/core/osinfo.py
dan/core/pathlib.py
dan/core/pm.py
dan/core/register.py
dan/core/requirements.py
dan/core/runners.py
dan/core/settings.py
dan/core/target.py
dan/core/terminal.py
dan/core/test.py
dan/core/typing.py
dan/core/utils.py
dan/core/version.py
dan/core/win.py
dan/cxx/__init__.py
dan/cxx/compile_commands.py
dan/cxx/detect.py
dan/cxx/ldd.py
dan/cxx/msvc_toolchain.py
dan/cxx/targets.py
dan/cxx/toolchain.py
dan/cxx/unix_toolchain.py
dan/cxx/data/__init__.py
dan/cxx/data/detect.cmd
dan/cxx/data/empty.c
dan/cxx/support/__init__.py
dan/cxx/support/qt.py
dan/io/__init__.py
dan/io/package.py
dan/io/repositories.py
dan/pkgconfig/__init__.py
dan/pkgconfig/package.py
dan/pkgconfig/templates/__init__.py
dan/pkgconfig/templates/pkg.pc.jinja2
dan/src/__init__.py
dan/src/base.py
dan/src/git.py
dan/src/github.py
dan/src/tar.py
dan/utils/__init__.py
dan/utils/net.py
dan_build-0.2.10.data/data/etc/bash_completion.d/dan-io.sh
dan_build-0.2.10.data/data/etc/bash_completion.d/dan.sh
dan_build-0.2.10.data/data/etc/zsh_completion.d/dan-io.sh
dan_build-0.2.10.data/data/etc/zsh_completion.d/dan.sh
dan_build-0.2.10.dist-info/LICENSE
dan_build-0.2.10.dist-info/METADATA
dan_build-0.2.10.dist-info/WHEEL
dan_build-0.2.10.dist-info/entry_points.txt
dan_build-0.2.10.dist-info/top_level.txt
dan_build-0.2.10.dist-info/RECORD
