Metadata-Version: 2.1
Name: dan-build
Version: 0.2.10
Summary: Python-based build system.
Author-email: Garcia Sylvain <garcia.6l20@gmail.com>, garcia.6l20@gmail.com
License: MIT License
Project-URL: homepage, https://github.com/Garcia6L20/dan
Project-URL: documentation, https://github.com/Garcia6L20/dan
Project-URL: repository, https://github.com/Garcia6L20/dan
Keywords: packaging,dependency,build system
Classifier: Topic :: Software Development
Requires-Python: >=3.10
License-File: LICENSE
Requires-Dist: click >=8.0.0
Requires-Dist: jinja2
Requires-Dist: distro
Requires-Dist: pyyaml
Requires-Dist: aiofiles
Requires-Dist: aiohttp
Requires-Dist: async-property >=0.2.2
Requires-Dist: termcolor
Requires-Dist: importlib-metadata
Requires-Dist: dataclasses-json
Requires-Dist: lockfile
Requires-Dist: pefile
Requires-Dist: pyelftools
